{"assets":{"38B7783F0074B32A6FB166CA186F8AE8":{"type":"texture","index":1,"assetRequest":{"type":"slide","state":"contents","slide":"none"},"url":{"native":"assets\/88C45D1F-56A3-41D9-8E69-FB0E1226145F.pdf"},"width":1920,"height":1080},"30CF55524FCC9C939D202F500AE07DDC":{"type":"texture","index":0,"assetRequest":{"type":"slide","state":"contents","slide":"none"},"url":{"native":"assets\/88C45D1F-56A3-41D9-8E69-FB0E1226145F.pdf"},"width":1920,"height":1080}},"events":[{"effects":[{"beginTime":0,"baseLayer":{"animations":[],"initialState":{"affineTransform":[1,0,0,1,0,0],"masksToBounds":false,"rotation":0,"scale":1,"position":{"pointX":960,"pointY":540},"width":1920,"sublayerTransform":[1,0,0,0,0,1,0,0,0,0,1,0,0,0,0,1],"contentsRect":{"y":0,"x":0,"width":1,"height":1},"opacity":1,"edgeAntialiasingMask":251658240,"height":1080,"hidden":false,"anchorPoint":{"pointX":0.5,"pointY":0.5}},"objectID":"0","layers":[{"animations":[],"initialState":{"affineTransform":[1,0,0,1,0,0],"masksToBounds":false,"rotation":0,"scale":1,"position":{"pointX":960,"pointY":540},"width":1920,"sublayerTransform":[1,0,0,0,0,1,0,0,0,0,1,-0.00035007912466775983,0,0,0,1],"contentsRect":{"y":0,"x":0,"width":1,"height":1},"opacity":1,"edgeAntialiasingMask":251658240,"height":1080,"hidden":false,"anchorPoint":{"pointX":0.5,"pointY":0.5}},"layers":[{"animations":[],"layers":[],"texturedRectangle":{"isBackgroundTexture":false,"singleTextureOpacity":1,"textureType":0,"textBaseline":0,"textXHeight":0,"isVerticalText":false},"initialState":{"affineTransform":[1,0,0,1,0,0],"masksToBounds":false,"rotation":0,"scale":1,"position":{"pointX":960,"pointY":540},"width":1920,"sublayerTransform":[1,0,0,0,0,1,0,0,0,0,1,0,0,0,0,1],"contentsRect":{"y":0,"x":0,"width":1,"height":1},"opacity":1,"edgeAntialiasingMask":0,"height":1080,"hidden":false,"anchorPoint":{"pointX":0.5,"pointY":0.5}},"texture":"38B7783F0074B32A6FB166CA186F8AE8"},{"animations":[{"additive":false,"timeOffset":0,"beginTime":0,"from":{"scalar":false},"repeatCount":0,"fillMode":"both","duration":0.01,"autoreverses":false,"property":"hidden","to":{"scalar":true},"removedOnCompletion":false}],"layers":[],"texturedRectangle":{"isBackgroundTexture":false,"singleTextureOpacity":1,"textureType":0,"textBaseline":0,"textXHeight":0,"isVerticalText":false},"initialState":{"affineTransform":[1,0,0,1,0,0],"masksToBounds":false,"rotation":0,"scale":1,"position":{"pointX":960,"pointY":540},"width":1920,"sublayerTransform":[1,0,0,0,0,1,0,0,0,0,1,0,0,0,0,1],"contentsRect":{"y":0,"x":0,"width":1,"height":1},"opacity":1,"edgeAntialiasingMask":0,"height":1080,"hidden":false,"anchorPoint":{"pointX":0.5,"pointY":0.5}},"texture":"30CF55524FCC9C939D202F500AE07DDC"}]}]},"effects":[],"duration":0.01,"type":"transition","attributes":{"direction":0},"name":"none","objectID":"0"}],"automaticPlay":false,"hyperlinks":[],"accessibility":[{"text":"equation.pdf","targetRectangle":{"y":300.61790307844296,"x":1535.9691872898529,"width":176.22777777777765,"height":42.649999999999977}},{"text":"Bernoulli random variable","targetRectangle":{"y":24.693778991699219,"x":82.15789794921875,"width":927.26370099577071,"height":128}},{"text":"equation.pdf","targetRectangle":{"y":94.718169204612764,"x":1110.6466710886084,"width":737.69399999999996,"height":140.22}},{"text":"equation.pdf","targetRectangle":{"y":493.85859144213464,"x":493.75144630050625,"width":28.035588785046684,"height":75.985196407710305}},{"text":"equation.pdf","targetRectangle":{"y":681.44675032050282,"x":546.68744630050628,"width":255.67423145870907,"height":77.568221332870962}},{"text":"equation.pdf","targetRectangle":{"y":305.61790309029925,"x":1438.0849031031012,"width":34.200000000000045,"height":32.649999999999977}},{"text":"equation.pdf","targetRectangle":{"y":778.50132831148471,"x":169.89544475078549,"width":560.82953293408207,"height":71.236121632228446}},{"text":"A random variable for modeling binary events","targetRectangle":{"y":175.05858847978374,"x":169.89544630050625,"width":830.024,"height":71}},{"text":"Two possible outcomes: ","targetRectangle":{"y":231.85858932616969,"x":169.89544630050625,"width":439.76400000000001,"height":102}},{"text":"Success - value 1","targetRectangle":{"y":319.65859017255565,"x":217.89544630050625,"width":302.43200000000002,"height":90}},{"text":"Failure - value 0","targetRectangle":{"y":367.05859059574863,"x":217.89544630050625,"width":287.04000000000002,"height":106}},{"text":"Single parameter ￼, probability of a success","targetRectangle":{"y":458.85859144213458,"x":169.89544630050625,"width":789.69558878504688,"height":110.98519640771025}},{"text":"multiple Bernoulli r.v. can be combined to model more complex random variables","targetRectangle":{"y":554.64674947411686,"x":169.89544630050625,"width":1482.3640000000005,"height":106}},{"text":"Shorthand notation: ￼","targetRectangle":{"y":646.44675032050282,"x":169.89544630050625,"width":632.4662314587091,"height":112.56822133287096}},{"text":"￼","targetRectangle":{"y":743.50132831148494,"x":169.89544475078549,"width":560.82953293408207,"height":106.23612163222833}},{"text":"equation.pdf","targetRectangle":{"y":452.64378676492083,"x":1539.2629381838578,"width":27.349999999999909,"height":32.300000000000011}},{"text":"equation.pdf","targetRectangle":{"y":375.93084511834491,"x":1543.0741677586029,"width":99.522222222222126,"height":44.050000000000011}}],"baseLayer":{"animations":[],"initialState":{"affineTransform":[1,0,0,1,0,0],"masksToBounds":false,"rotation":0,"scale":1,"position":{"pointX":960,"pointY":540},"width":1920,"sublayerTransform":[1,0,0,0,0,1,0,0,0,0,1,0,0,0,0,1],"contentsRect":{"y":0,"x":0,"width":1,"height":1},"opacity":1,"edgeAntialiasingMask":251658240,"height":1080,"hidden":false,"anchorPoint":{"pointX":0.5,"pointY":0.5}},"objectID":"0","layers":[{"animations":[],"initialState":{"affineTransform":[1,0,0,1,0,0],"masksToBounds":false,"rotation":0,"scale":1,"position":{"pointX":960,"pointY":540},"width":1920,"sublayerTransform":[1,0,0,0,0,1,0,0,0,0,1,-0.00035007912466775983,0,0,0,1],"contentsRect":{"y":0,"x":0,"width":1,"height":1},"opacity":1,"edgeAntialiasingMask":251658240,"height":1080,"hidden":false,"anchorPoint":{"pointX":0.5,"pointY":0.5}},"layers":[{"animations":[],"layers":[],"texturedRectangle":{"isBackgroundTexture":false,"singleTextureOpacity":1,"textureType":0,"textBaseline":0,"textXHeight":0,"isVerticalText":false},"initialState":{"affineTransform":[1,0,0,1,0,0],"masksToBounds":false,"rotation":0,"scale":1,"position":{"pointX":960,"pointY":540},"width":1920,"sublayerTransform":[1,0,0,0,0,1,0,0,0,0,1,0,0,0,0,1],"contentsRect":{"y":0,"x":0,"width":1,"height":1},"opacity":1,"edgeAntialiasingMask":0,"height":1080,"hidden":false,"anchorPoint":{"pointX":0.5,"pointY":0.5}},"texture":"30CF55524FCC9C939D202F500AE07DDC"}]}]}}]}